doc/attention.png
doc/benchmark_attention.png
doc/benchmark_t5.png
doc/benchmark_t5_original.png
grouped_query_attention_pytorch/__init__.py
grouped_query_attention_pytorch/attention.py
grouped_query_attention_pytorch/t5.py
grouped_query_attention_pytorch/transformer.py
grouped_query_attention_pytorch/utils/__init__.py
grouped_query_attention_pytorch/utils/benchmark.py
scripts/README.md
scripts/benchmark_attention.py
scripts/benchmark_t5.py
grouped_query_attention_pytorch-0.3.0.dist-info/LICENSE
grouped_query_attention_pytorch-0.3.0.dist-info/METADATA
grouped_query_attention_pytorch-0.3.0.dist-info/WHEEL
grouped_query_attention_pytorch-0.3.0.dist-info/top_level.txt
grouped_query_attention_pytorch-0.3.0.dist-info/RECORD
