Metadata-Version: 2.1
Name: grouped_query_attention_pytorch
Version: 0.3.0
Summary: grouped-query-attention-pytorch
Author-email: Frank Odom <frank.odom.iii@gmail.com>
License: MIT
Classifier: Programming Language :: Python :: 3
Requires-Python: >=3.8
License-File: LICENSE
Requires-Dist: einops ~=0.6.0
Requires-Dist: torch >=1.8.0
Requires-Dist: torchscale ~=0.2.0
Provides-Extra: t5
Requires-Dist: sentencepiece ; extra == 't5'
Requires-Dist: transformers <4.32,>=4.5.0 ; extra == 't5'
Provides-Extra: test
Requires-Dist: black ; extra == 'test'
Requires-Dist: kaleido ; extra == 'test'
Requires-Dist: mypy ; extra == 'test'
Requires-Dist: plotly ; extra == 'test'
Requires-Dist: pre-commit ; extra == 'test'
Requires-Dist: pytest ; extra == 'test'
Requires-Dist: pytest-cov ; extra == 'test'
Requires-Dist: ruff ; extra == 'test'
Requires-Dist: xformers ==0.0.20 ; extra == 'test'
